universalizer/__init__.py
universalizer/categories.py
universalizer/cli.py
universalizer/norm.py
universalizer/oak_utils.py
universalizer-0.0.12.dist-info/LICENSE
universalizer-0.0.12.dist-info/METADATA
universalizer-0.0.12.dist-info/WHEEL
universalizer-0.0.12.dist-info/entry_points.txt
universalizer-0.0.12.dist-info/RECORD
