Metadata-Version: 2.3
Name: universalizer
Version: 0.0.12
Summary: Provides functions for knowledge graph cleanup and identifier normalization.
License: BSD-3
Keywords: kg-hub,knowledgegraphs,ontology
Author: caufieldjh
Author-email: j.harry.caufield@gmail.com
Requires-Python: >=3.9,<3.13
Classifier: Environment :: Console
Classifier: Intended Audience :: Science/Research
Classifier: License :: Other/Proprietary License
Classifier: Programming Language :: Python :: 3
Classifier: Programming Language :: Python :: 3.9
Classifier: Programming Language :: Python :: 3.10
Classifier: Programming Language :: Python :: 3.11
Classifier: Programming Language :: Python :: 3.12
Requires-Dist: click (>=8.1.3,<9.0.0)
Requires-Dist: kgx (>=2.0.0)
Requires-Dist: oaklib (>=0.5.10)
Requires-Dist: prefixmaps (>=0.2.5)
Project-URL: Repository, https://github.com/Knowledge-Graph-Hub/universalizer
